niceapp_hoge/__init__.py
niceapp_hoge/__main__.py
niceapp_hoge-0.1.0.dist-info/METADATA
niceapp_hoge-0.1.0.dist-info/WHEEL
niceapp_hoge-0.1.0.dist-info/entry_points.txt
niceapp_hoge-0.1.0.dist-info/RECORD
